aiohttp_simple-0.1.7.dist-info/METADATA
aiohttp_simple-0.1.7.dist-info/WHEEL
aiohttp_simple-0.1.7.dist-info/entry_points.txt
aiohttp_simple/__init__.py
aiohttp_simple/__main__.py
aiohttp_simple/data/config/config.json
aiohttp_simple/data/config/config.yaml
aiohttp_simple/data/config/config_di.yaml
aiohttp_simple/data/config/log.yaml
aiohttp_simple/data/example.py
aiohttp_simple/middlewares/__init__.py
aiohttp_simple/middlewares/check.py
aiohttp_simple/middlewares/db.py
aiohttp_simple/template/__init__.py
aiohttp_simple/template/data_model.py
aiohttp_simple/template/db_table.py
aiohttp_simple/template/response.py
aiohttp_simple/template/service.py
aiohttp_simple/utils/__init__.py
aiohttp_simple/utils/contextvar.py
aiohttp_simple/utils/log.py
aiohttp_simple/utils/manual.py
aiohttp_simple/utils/setting.py
aiohttp_simple-0.1.7.dist-info/RECORD
