Metadata-Version: 2.1
Name: aiohttp-simple
Version: 0.1.7
Summary: simplify the use of aiohttp
Author-Email: gnakw <gnakw@outlook.com>
License: MIT
Requires-Python: >=3.10
Requires-Dist: aiohttp>=3.8.6
Requires-Dist: pydantic>=2.4.2
Requires-Dist: pydantic-settings>=2.0.3
Requires-Dist: sqlalchemy>=2.0.23
Requires-Dist: pyyaml>=6.0.1
Requires-Dist: aiomysql>=0.2.0
